{"cameraMode":{"drawMode":0,"name":"Shaded","section":"Shading Mode"},"sceneLighting":false,"audioPlay":false,"sceneViewState":{"m_AlwaysRefresh":false,"showFog":true,"showSkybox":false,"showFlares":true,"showImageEffects":true,"showParticleSystems":true,"showVisualEffectGraphs":true,"m_FxEnabled":true},"in2DMode":false,"pivot":{"x":80.0,"y":-20.0,"z":0.0},"rotation":{"x":0.15239550173282624,"y":0.010377133265137673,"z":-0.0016002089250832797,"w":0.9882651567459106},"size":10.319883346557618,"orthographic":false}