{"cameraMode":{"drawMode":0,"name":"Shaded","section":"Shading Mode"},"sceneLighting":false,"audioPlay":false,"sceneViewState":{"m_AlwaysRefresh":false,"showFog":true,"showSkybox":false,"showFlares":true,"showImageEffects":true,"showParticleSystems":true,"showVisualEffectGraphs":true,"m_FxEnabled":true},"in2DMode":false,"pivot":{"x":3.690000057220459,"y":4.0,"z":0.0},"rotation":{"x":0.11049728840589524,"y":0.07000810652971268,"z":-0.007803179323673248,"w":0.9913783669471741},"size":4.3023247718811039,"orthographic":false}